odoo/addons/l10n_it_bill_of_entry/README.rst
odoo/addons/l10n_it_bill_of_entry/__init__.py
odoo/addons/l10n_it_bill_of_entry/__manifest__.py
odoo/addons/l10n_it_bill_of_entry/demo/bill_of_entry_demo.xml
odoo/addons/l10n_it_bill_of_entry/i18n/it.po
odoo/addons/l10n_it_bill_of_entry/i18n/l10n_it_bill_of_entry.pot
odoo/addons/l10n_it_bill_of_entry/migrations/13.0.1.0.0/post-migration.py
odoo/addons/l10n_it_bill_of_entry/migrations/13.0.1.0.0/pre-migration.py
odoo/addons/l10n_it_bill_of_entry/models/__init__.py
odoo/addons/l10n_it_bill_of_entry/models/account_move.py
odoo/addons/l10n_it_bill_of_entry/models/company.py
odoo/addons/l10n_it_bill_of_entry/readme/CONFIGURE.rst
odoo/addons/l10n_it_bill_of_entry/readme/CONTRIBUTORS.rst
odoo/addons/l10n_it_bill_of_entry/readme/DESCRIPTION.rst
odoo/addons/l10n_it_bill_of_entry/readme/USAGE.rst
odoo/addons/l10n_it_bill_of_entry/static/description/icon.png
odoo/addons/l10n_it_bill_of_entry/static/description/index.html
odoo/addons/l10n_it_bill_of_entry/tests/__init__.py
odoo/addons/l10n_it_bill_of_entry/tests/test_bill_of_entry.py
odoo/addons/l10n_it_bill_of_entry/views/account_invoice_view.xml
odoo/addons/l10n_it_bill_of_entry/views/company_view.xml
odoo14_addon_l10n_it_bill_of_entry-14.0.1.0.2.dist-info/METADATA
odoo14_addon_l10n_it_bill_of_entry-14.0.1.0.2.dist-info/WHEEL
odoo14_addon_l10n_it_bill_of_entry-14.0.1.0.2.dist-info/top_level.txt
odoo14_addon_l10n_it_bill_of_entry-14.0.1.0.2.dist-info/RECORD
