Metadata-Version: 2.1
Name: odoo14-addon-l10n-it-bill-of-entry
Version: 14.0.1.0.2
Summary: ITA - Bolle doganali
Home-page: https://github.com/OCA/l10n-italy/tree/12.0/l10n_it_bill_of_entry
Author: Agile Business Group, CQ Creativi Quadrati, TAKOBI, Odoo Community Association (OCA)
Author-email: support@odoo-community.org
License: AGPL-3
Platform: UNKNOWN
Classifier: Programming Language :: Python
Classifier: Framework :: Odoo
Classifier: Framework :: Odoo :: 14.0
Classifier: License :: OSI Approved :: GNU Affero General Public License v3
Requires-Python: >=3.6
Requires-Dist: odoo <14.1dev,>=14.0a
